[{"company_id": "DYN-CORP-0001", "legal_name": "Dynime Limited", "trade_name": "Dynime", "founded": "2020-01-15", "ceo": "Imran R. Khan", "cfo": "Sadia Nahar", "cto": "Tanvir Mahmud", "hq_country": "Bangladesh", "hq_address": "Plot 3 & 5, bti Celebration Point, Rd 113/A, Gulshan, Dhaka-1212", "registered_offices": "Dhaka (BD) \u00b7 London (UK) \u00b7 Albany NY (US)", "tax_id_bd": "BIN-002148-3719-0220", "vat_uk": "GB-413-8821-77", "ein_us": "85-3924108", "industry": "Digital Services + SaaS", "website": "https://dynime.com", "support_email": "support@dynime.com", "billing_email": "billing@dynime.com", "fiscal_year_start": "July 01", "reporting_currency": "USD", "bankers": "HSBC (UK) \u00b7 Brac Bank (BD) \u00b7 Mercury (US)", "auditor": "Hoda Vasi Chowdhury & Co."}]